Structuralia/AccessPDB.py
Structuralia/GlobalVars.py
Structuralia/KnotScope.py
Structuralia/OligoState.py
Structuralia/OligoSum.py
Structuralia/TimeWrap.py
Structuralia/Toolbox.py
Structuralia/__init__.py
Structuralia-0.912.dist-info/DESCRIPTION.rst
Structuralia-0.912.dist-info/METADATA
Structuralia-0.912.dist-info/RECORD
Structuralia-0.912.dist-info/WHEEL
Structuralia-0.912.dist-info/entry_points.txt
Structuralia-0.912.dist-info/metadata.json
Structuralia-0.912.dist-info/top_level.txt
