Metadata-Version: 2.0
Name: Structuralia
Version: 0.912
Summary: A toolset to work with proteins
Home-page: https://github.com/monteirotorres/Structuralia
Author: Pedro Torres
Author-email: monteirotorres@gmail.com
License: UNKNOWN
Download-URL: https://github.com/monteirotorres/Structuralia/archive/0.912.tar.gz
Keywords: PDB,structure,protein
Platform: UNKNOWN
Requires-Dist: markdown
Requires-Dist: biopandas
Requires-Dist: pandas
Requires-Dist: progressbar2
Requires-Dist: pathlib2
Requires-Dist: biopython
Requires-Dist: parasail
